LICENSE
README.md
setup.py
pyrandomify/__init__.py
pyrandomify.egg-info/PKG-INFO
pyrandomify.egg-info/SOURCES.txt
pyrandomify.egg-info/dependency_links.txt
pyrandomify.egg-info/top_level.txt
pyrandomify/digits/__init__.py
pyrandomify/digits/digits.py
pyrandomify/enums/__init__.py
pyrandomify/enums/types.py
pyrandomify/generate/__init__.py
pyrandomify/generate/generate.py
pyrandomify/text/__init__.py
pyrandomify/text/text.py