Metadata-Version: 2.1
Name: pyrandomify
Version: 1.1
Summary: A simple module for convenient and fast generation of a character set
Home-page: https://github.com/frymex/randomify
Author: Nikita Protect
Author-email: t_frymex@proton.me
License: BSD 2-clause
Keywords: random randomify python-random
Platform: UNKNOWN
Classifier: Development Status :: 3 - Alpha
Classifier: Topic :: Utilities
Classifier: License :: OSI Approved :: BSD License
Classifier: Programming Language :: Python :: 3.9
Classifier: Programming Language :: Python :: 3.10
Classifier: Programming Language :: Python :: 3.11
Classifier: Programming Language :: Python :: 3.12
License-File: LICENSE
